{"sections":{"48edaa1f-b582-470b-8d04-40d80341942b":{"type":"product-slider","blocks":{"template--19713839202582__48edaa1f-b582-470b-8d04-40d80341942b-16887928979aa24c83-0":{"type":"product_slide","settings":{"image":"shopify:\/\/shop_images\/banner4Ringmerry.jpg","product":"","subheading":"","color_text":"#282828","show_subheading_dot":true,"color_dot":"#40b66f","heading":"Fusion Of Jewelry And Technology","text":"Impress your customers with our cutting-edge rendering technology and selection from millions of CADs, images and videos and build your online store"}},"template--19713839202582__48edaa1f-b582-470b-8d04-40d80341942b-16887928979aa24c83-1":{"type":"product_slide","settings":{"image":"shopify:\/\/shop_images\/7.jpg","product":"","subheading":"","color_text":"#282828","show_subheading_dot":true,"color_dot":"#40b66f","heading":"For All Your Digital Marketing Needs","text":"We are your trusted partner in navigating the ever-evolving digital landscape."}},"template--19713839202582__48edaa1f-b582-470b-8d04-40d80341942b-16887928979aa24c83-2":{"type":"product_slide","settings":{"image":"shopify:\/\/shop_images\/5.jpg","product":"","subheading":"","color_text":"#282828","show_subheading_dot":true,"color_dot":"#40b66f","heading":"Rendered Videos & Images","text":"CAD | Rendering | Photography"}},"33c6ae53-49e6-4115-91a4-0f2ecbcfc4c0":{"type":"product_slide","settings":{"image":"shopify:\/\/shop_images\/banner4_1.jpg","product":"","subheading":"","color_text":"#282828","show_subheading_dot":true,"color_dot":"#40b66f","heading":"One Stop E-Commerce Solutions","text":"Take your business from a \nbrick-and-mortar storefront to the World Wide Web !\nEverything you need in one place!"}}},"block_order":["template--19713839202582__48edaa1f-b582-470b-8d04-40d80341942b-16887928979aa24c83-0","template--19713839202582__48edaa1f-b582-470b-8d04-40d80341942b-16887928979aa24c83-1","template--19713839202582__48edaa1f-b582-470b-8d04-40d80341942b-16887928979aa24c83-2","33c6ae53-49e6-4115-91a4-0f2ecbcfc4c0"],"custom_css":[".product-slider__text {font-weight: 300; font-family: \"Poppins\"; text-align: start;}","h2 {text-align: start; font-weight: 300; font-family: \"Poppins\";}"],"settings":{"color_scheme":"2","desktop_alignment":"right","mobile_alignment":"before","image_fit":"cover","slide_duration":3,"show_vendor":true,"image_ratio":"landscape","image_fit_card":"cover","margin_top":"no-indent","margin_bottom":"no-indent","padding_top":"no-indent","padding_bottom":"no-indent"}},"5ed7c7e5-b0f1-42d6-9aa0-897eafcf4df6":{"type":"multicolumn","blocks":{"template--19713839202582__5ed7c7e5-b0f1-42d6-9aa0-897eafcf4df6-1688801151de20c9cf-0":{"type":"column","settings":{"image":"shopify:\/\/shop_images\/3d-rendering.png","heading":"Pristine Quality Rendered Images & Videos","text":""}},"template--19713839202582__5ed7c7e5-b0f1-42d6-9aa0-897eafcf4df6-1688801151de20c9cf-1":{"type":"column","settings":{"image":"shopify:\/\/shop_images\/coding.png","heading":"Website Development","text":""}},"template--19713839202582__5ed7c7e5-b0f1-42d6-9aa0-897eafcf4df6-1688801151de20c9cf-2":{"type":"column","settings":{"image":"shopify:\/\/shop_images\/bullhorn.png","heading":"Effective & Efficient Social Media Marketing","text":""}}},"block_order":["template--19713839202582__5ed7c7e5-b0f1-42d6-9aa0-897eafcf4df6-1688801151de20c9cf-0","template--19713839202582__5ed7c7e5-b0f1-42d6-9aa0-897eafcf4df6-1688801151de20c9cf-1","template--19713839202582__5ed7c7e5-b0f1-42d6-9aa0-897eafcf4df6-1688801151de20c9cf-2"],"custom_css":[".multicolumn-list__wrapper .multicolumn-card__heading {font-weight: 300; font-family: \"Poppins\";}"],"settings":{"color_scheme":"background-1","multicolumn_to_show":3,"image_type":"icon","icon_background":"background-2","image_width":"medium","object_fit":"contain","swipe_on_mobile":true,"border_top":false,"margin_top":"no-indent","margin_bottom":"no-indent","padding_top":"xs","padding_bottom":"no-indent"}},"cards-grid":{"type":"cards-grid","disabled":true,"blocks":{"block_1":{"type":"column","settings":{"column_start":1,"column_end":3,"row_start":"1","row_end":"3","min_height":"small","padding":"small","image":"shopify:\/\/shop_images\/silver-ring-with-diamonds-it-word-diamonds-it.jpg","image_size":"cover","icon_size":"cover","icon_position":"left-top","icon_background":"background-2","background_color":"#ffffff","background_effect":"none","effect_opacity":0.9,"enable_mobile_overlay":false,"text_align":"bottom-left","text_color_scheme":"dark","subheading":"","color_text":"#282828","show_subheading_dot":false,"color_dot":"#40b66f","heading":"","heading_size":"h3","heading_width":100,"text":"","text_size":"medium","text_width":100,"show_button":false,"button_label":"Explore Our Store","button_link":"shopify:\/\/collections","style_button":"button button--primary button--arrow","add_button_label":"","add_button_price":"","card_link":""}},"block_2":{"type":"column","settings":{"column_start":3,"column_end":4,"row_start":"1","row_end":"3","min_height":"small","padding":"small","image":"shopify:\/\/shop_images\/close-up-of-a-hand-with-a-ring-on-it.jpg","image_size":"cover","icon_size":"cover","icon_position":"left-top","icon_background":"background-2","background_color":"#ffffff","background_effect":"none","effect_opacity":0.4,"enable_mobile_overlay":false,"text_align":"left","text_color_scheme":"dark","subheading":"","color_text":"#282828","show_subheading_dot":false,"color_dot":"#40b66f","heading":"","heading_size":"h3","heading_width":50,"text":"","text_size":"small","text_width":100,"show_button":false,"button_label":"Explore Our Store","button_link":"","style_button":"button button--primary button--arrow","add_button_label":"","add_button_price":"","card_link":""}},"block_3":{"type":"column","settings":{"column_start":4,"column_end":5,"row_start":"auto","row_end":"auto","min_height":"small","padding":"small","image":"shopify:\/\/shop_images\/shiny-gemstone-ring-platinum-luxury-elegance-captured-generated-by-ai.jpg","image_size":"cover","icon_size":"cover","icon_position":"left-top","icon_background":"background-2","background_color":"#ffffff","background_effect":"none","effect_opacity":0.4,"enable_mobile_overlay":false,"text_align":"left","text_color_scheme":"dark","subheading":"","color_text":"#282828","show_subheading_dot":false,"color_dot":"#40b66f","heading":"","heading_size":"h3","heading_width":50,"text":"","text_size":"small","text_width":100,"show_button":false,"button_label":"Explore Our Store","button_link":"","style_button":"button button--primary button--arrow","add_button_label":"","add_button_price":"","card_link":""}},"block_4":{"type":"column","settings":{"column_start":4,"column_end":5,"row_start":"auto","row_end":"auto","min_height":"small","padding":"small","image":"shopify:\/\/shop_images\/silver-ring-with-diamonds-it-word-diamonds-it_04643b27-ee71-4dc2-b386-4233c2c5be66.jpg","image_size":"cover","icon_size":"cover","icon_position":"left-top","icon_background":"background-2","background_color":"#ffffff","background_effect":"none","effect_opacity":0.4,"enable_mobile_overlay":false,"text_align":"left","text_color_scheme":"dark","subheading":"","color_text":"#282828","show_subheading_dot":false,"color_dot":"#40b66f","heading":"","heading_size":"h3","heading_width":50,"text":"","text_size":"small","text_width":100,"show_button":false,"button_label":"Explore Our Store","button_link":"","style_button":"button button--primary button--arrow","add_button_label":"","add_button_price":"","card_link":""}}},"block_order":["block_1","block_2","block_3","block_4"],"settings":{"color_scheme":"background-1","columns":4,"margin_top":"no-indent","margin_bottom":"no-indent","padding_top":"no-indent","padding_bottom":"no-indent"}},"56f7c8aa-88c7-485a-a999-271f3264f443":{"type":"multicolumn","blocks":{"template--19713839202582__56f7c8aa-88c7-485a-a999-271f3264f443-1688801151de20c9cf-0":{"type":"column","settings":{"image":"shopify:\/\/shop_images\/creative-writing.png","heading":"Content Creation","text":""}},"template--19713839202582__56f7c8aa-88c7-485a-a999-271f3264f443-1688801151de20c9cf-1":{"type":"column","settings":{"image":"shopify:\/\/shop_images\/ads-campaign.png","heading":"Campaign Management","text":""}},"template--19713839202582__56f7c8aa-88c7-485a-a999-271f3264f443-1688801151de20c9cf-2":{"type":"column","settings":{"image":"shopify:\/\/shop_images\/growth.png","heading":"Increase Sales","text":""}}},"block_order":["template--19713839202582__56f7c8aa-88c7-485a-a999-271f3264f443-1688801151de20c9cf-0","template--19713839202582__56f7c8aa-88c7-485a-a999-271f3264f443-1688801151de20c9cf-1","template--19713839202582__56f7c8aa-88c7-485a-a999-271f3264f443-1688801151de20c9cf-2"],"custom_css":[".multicolumn-list__wrapper .multicolumn-card__heading {font-weight: 300; font-family: \"Poppins\";}"],"settings":{"color_scheme":"background-1","multicolumn_to_show":3,"image_type":"icon","icon_background":"background-2","image_width":"medium","object_fit":"contain","swipe_on_mobile":true,"border_top":false,"margin_top":"no-indent","margin_bottom":"no-indent","padding_top":"xs","padding_bottom":"no-indent"}},"featured-products":{"type":"featured-products","custom_css":[".featured-products__text {text-decoration: none; font-weight: 300; font-family: \"Poppins\"; line-height: 1.8;}","h2 {font-weight: 300; font-family: \"Poppins\";}"],"settings":{"color_scheme":"background-1","subheading":"","heading":"","heading_size":"h2","show_info":true,"info_subheading":"","info_heading":"THE MYRIAD COLLECTION OF ULTIMATE DESIGN","info_heading_size":"h2","text":"Introducing \"The Myriad Collection of Ultimate Design\" ring, a stunning assortment of exquisite rings crafted with meticulous attention to detail. Each ring from this collection showcases a harmonious blend of timeless elegance and contemporary style, designed to captivate and adorn.","show_button":true,"button_style":"secondary","button_label":"Explore Our Store","button_link":"shopify:\/\/collections\/collection","product_list":["ringmerry-3","ringmerry","glam-jam-ring","maria-emerald-cut-ring","paige-diamond-eternity-ring","pebel-two-stone-ring","petite-diamond-bracelet","brilliant-triple-row-engagement-ring","aldora-barcelet","flex-bracelet","french-pave-engagement-ring","fantasy-channel-ring"],"columns_mobile":"1","image_ratio":"square","image_fit":"cover","show_secondary_image":true,"show_vendor":true,"show_desc":false,"margin_top":"no-indent","margin_bottom":"no-indent","padding_top":"xs","padding_bottom":"no-indent"}},"f985f678-f3e0-4940-a56f-227b4d758eb8":{"type":"countdown","disabled":true,"settings":{"section_type":"simple","date_picker":"2024-03-01","time_picker":"00:00","cursive_date":false,"countdown_block_font":50,"completed_countdown":"show_text","countdown_heading":"<p>Header after countdown<\/p>","image":"shopify:\/\/shop_images\/blue-and-green-background-with-silver-jewelry.jpg","opacity_overlay":0.6,"heading":"Some header","text":"Some description.","show_link":true,"button_label":"Shop now","button_style":"primary","button_link":"","margin_top":"no-indent","margin_bottom":"no-indent","padding_top":"m","padding_bottom":"no-indent"}},"product-promo":{"type":"product-promo","disabled":true,"blocks":{"block_1":{"type":"column","disabled":true,"settings":{"image_size":"cover","opacity_overlay":0.1,"background_color":"#cccccc","product":"","text_color_scheme":"dark","subheading":"Subheading","color_text":"#282828","show_subheading_dot":false,"color_dot":"#40b66f","heading":"Heading","heading_size":"h2","text":"Some description","show_button":false,"button_style":"primary","button_label":"Explore Our Store","button_link":""}},"block_2":{"type":"column","disabled":true,"settings":{"image_size":"cover","opacity_overlay":0.1,"background_color":"#cccccc","product":"","text_color_scheme":"dark","subheading":"Subheading","color_text":"#282828","show_subheading_dot":false,"color_dot":"#40b66f","heading":"Heading","heading_size":"h2","text":"Some description","show_button":false,"button_style":"primary","button_label":"Explore Our Store","button_link":""}}},"block_order":["block_1","block_2"],"settings":{"color_scheme":"background-1","columns_per_row":"2","margin_top":"no-indent","margin_bottom":"no-indent","padding_top":"m","padding_bottom":"no-indent","image_ratio":"square","image_fit":"cover","show_secondary_image":false,"show_vendor":true}},"multicolumn":{"type":"multicolumn","disabled":true,"blocks":{"column-1":{"type":"column","settings":{"heading":"Heading","text":"Description"}},"column-2":{"type":"column","settings":{"heading":"Heading","text":"Description"}},"column-3":{"type":"column","settings":{"heading":"Heading","text":"Description"}},"column-4":{"type":"column","settings":{"heading":"Heading","text":"Description"}}},"block_order":["column-1","column-2","column-3","column-4"],"settings":{"color_scheme":"background-1","multicolumn_to_show":4,"image_type":"image","icon_background":"background-2","image_width":"medium","object_fit":"contain","swipe_on_mobile":true,"border_top":false,"margin_top":"no-indent","margin_bottom":"no-indent","padding_top":"m","padding_bottom":"no-indent"}},"featured-product":{"type":"featured-product","disabled":true,"blocks":{"block_1":{"type":"text","settings":{"text":"Text block","vendor_url":""}},"block_2":{"type":"rating","settings":{}},"block_3":{"type":"title","settings":{"heading_size":"h2"}},"block_4":{"type":"price","settings":{}},"block_5":{"type":"variant_picker","settings":{"picker_type":"button"}},"block_6":{"type":"buy_buttons","settings":{"show_dynamic_checkout":true,"show_quantity":true}}},"block_order":["block_1","block_2","block_3","block_4","block_5","block_6"],"settings":{"product_item":"silver-ring","color_scheme":"background-2","heading":"","padding_top":"m","padding_bottom":"no-indent"}},"popular-products":{"type":"popular-products","settings":{"heading":"Ringmerry collection","collection_list":["solitaire","eternity-rings"],"products_limit":12,"products_to_show":4,"filter":true,"filter_type":"collections","show_vendor":true,"image_ratio":"square","image_fit":"cover","padding_top":"xs","padding_bottom":"xs"}},"b1d9d440-f506-456a-86a8-3df1859c32e5":{"type":"rich-text","disabled":true,"blocks":{"template--19713839202582__b1d9d440-f506-456a-86a8-3df1859c32e5-subheading-1":{"type":"subheading","settings":{"subheading":""}},"template--19713839202582__b1d9d440-f506-456a-86a8-3df1859c32e5-heading-1":{"type":"heading","disabled":true,"settings":{"heading":"<p>Crafting Branch: From Vision to Effective Mangement<\/p>","heading_size":"medium"}},"template--19713839202582__b1d9d440-f506-456a-86a8-3df1859c32e5-text-1":{"type":"text","disabled":true,"settings":{"text":"<p>Your Product's Journey, Our Expertise: Partner with Our Skilled Graphic Designers, 3D Visualizers,  and Marketing Managers to Take Your Vision from Conceptualization to Full-Scale Commercialization and Beyond.<\/p>"}},"template--19713839202582__b1d9d440-f506-456a-86a8-3df1859c32e5-button-1":{"type":"button","disabled":true,"settings":{"button_label":"Button label","button_link":"","button_style":"primary"}}},"block_order":["template--19713839202582__b1d9d440-f506-456a-86a8-3df1859c32e5-subheading-1","template--19713839202582__b1d9d440-f506-456a-86a8-3df1859c32e5-heading-1","template--19713839202582__b1d9d440-f506-456a-86a8-3df1859c32e5-text-1","template--19713839202582__b1d9d440-f506-456a-86a8-3df1859c32e5-button-1"],"custom_css":["h2 {font-weight: 300; font-family: \"Poppins\";}","p {font-weight: 300; font-family: \"Poppins\"; line-height: 1.8;}"],"settings":{"color_scheme":"background-2","full_width":true,"margin_top":"no-indent","margin_bottom":"no-indent","padding_top":"xs","padding_bottom":"xs"}},"81962f3e-586c-417a-9567-dbeea81ebf11":{"type":"slideshow","blocks":{"template--18876850438419__81962f3e-586c-417a-9567-dbeea81ebf11-16831840189de12f5f-0":{"type":"slide","settings":{"color_scheme":"background-3","subheading":"","heading":"","heading_size":"medium","description":"","show_button":false,"button_style":"primary","button_label":"Explore Our Store","button_link":"","image":"shopify:\/\/shop_images\/3_5d3e5f30-48e0-4920-80aa-83ae1e01fa9d.jpg","overlay_opacity":0}},"template--18876850438419__81962f3e-586c-417a-9567-dbeea81ebf11-16831840189de12f5f-1":{"type":"slide","disabled":true,"settings":{"color_scheme":"background-3","subheading":"Subheading","heading":"Some heading","heading_size":"medium","description":"Some description","show_button":true,"button_style":"primary","button_label":"Explore Our Store","button_link":"","overlay_opacity":0.5}},"600f1105-7626-482f-9aad-56925783264d":{"type":"slide","disabled":true,"settings":{"color_scheme":"background-3","subheading":"Subheading","heading":"Some heading","heading_size":"medium","description":"Some description","show_button":true,"button_style":"primary","button_label":"Explore Our Store","button_link":"","overlay_opacity":0.5}}},"block_order":["template--18876850438419__81962f3e-586c-417a-9567-dbeea81ebf11-16831840189de12f5f-0","template--18876850438419__81962f3e-586c-417a-9567-dbeea81ebf11-16831840189de12f5f-1","600f1105-7626-482f-9aad-56925783264d"],"settings":{"color_scheme":"background-1","full_width":true,"height":"adapt","enable_autoplay":false,"slide_duration":5,"controls_color_scheme":"light","padding_top":"no-indent","padding_bottom":"no-indent","margin_top":"no-indent","margin_bottom":"no-indent"}},"2a8c50a3-1cc0-4611-a321-c6569ecb5710":{"type":"video","settings":{"full_width":true,"height":"16\/9","video_fit":"cover","subheading":"Subheading","heading":"Heading for your video","opacity_overlay":0,"video":"shopify:\/\/files\/videos\/Ringmarry_1 Min  Edit_2 (1).mp4","video_url":"https:\/\/www.youtube.com\/watch?v=_9VUPq3SxOc","video_autoplay":true,"video_loop":true,"video_muted":false,"video_controls":false,"description":"","margin_top":"no-indent","margin_bottom":"no-indent"}},"dc026c9c-e5f6-4e93-8b42-f40b32773c40":{"type":"image-banner","settings":{"full_width":true,"color_scheme":"background-1","subheading":"","heading":"","heading_size":"medium","text_information":"","text_align":"left","show_view_all":false,"button_label":"Shop now","button_style":"primary","button_link":"","image":"shopify:\/\/shop_images\/Digital-tansformation-1.png","image_ratio":"adapt","opacity_overlay":0,"margin_top":"no-indent","margin_bottom":"no-indent"}},"categories-list":{"type":"categories-list","blocks":{"collection_1":{"type":"collection_item","settings":{"collection":"solitaire","image":"shopify:\/\/shop_images\/Ring-12-WG0004_1.png"}},"collection_2":{"type":"collection_item","settings":{"collection":"eternity-rings","image":"shopify:\/\/shop_images\/rabd00614-wg0001.png"}},"collection_3":{"type":"collection_item","settings":{"collection":"stackable-bracelets","image":"shopify:\/\/shop_images\/raab002914-wg0001.png"}},"collection_4":{"type":"collection_item","settings":{"collection":"stackable-necklace","image":"shopify:\/\/shop_images\/rahe041814-wg0001.png"}},"collection_5":{"type":"collection_item","settings":{"collection":"stackable-rings","image":"shopify:\/\/shop_images\/raser0305349-wg0001.png"}},"collection_6":{"type":"collection_item","disabled":true,"settings":{"collection":"","image":"shopify:\/\/shop_images\/raser030512814-wg0001.png"}}},"block_order":["collection_1","collection_2","collection_3","collection_4","collection_5","collection_6"],"custom_css":[".categories-list__link {font-weight: 300; font-family: \"Poppins\";}"],"settings":{"color_scheme":"background-1","heading":"Authentic Collection","image_ratio":"square","image_fit":"cover","collections_to_show":5,"padding_top":"xs","padding_bottom":"xs"}},"45725f46-1ba6-405c-95d4-d360b9a71f9f":{"type":"rich-text","blocks":{"template--19713839202582__45725f46-1ba6-405c-95d4-d360b9a71f9f-subheading-1":{"type":"subheading","settings":{"subheading":""}},"template--19713839202582__45725f46-1ba6-405c-95d4-d360b9a71f9f-heading-1":{"type":"heading","settings":{"heading":"<h2>A Perfect Blend of Craftsmanship and Technological Ingenuity<\/h2>","heading_size":"medium"}},"template--19713839202582__45725f46-1ba6-405c-95d4-d360b9a71f9f-text-1":{"type":"text","settings":{"text":"<p>Revolutionary new way to create renderings of your designs, using software that leverages the power of AI and machine learning to generate stunning images & videos.<\/p>"}},"template--19713839202582__45725f46-1ba6-405c-95d4-d360b9a71f9f-button-1":{"type":"button","disabled":true,"settings":{"button_label":"Button label","button_link":"","button_style":"primary"}}},"block_order":["template--19713839202582__45725f46-1ba6-405c-95d4-d360b9a71f9f-subheading-1","template--19713839202582__45725f46-1ba6-405c-95d4-d360b9a71f9f-heading-1","template--19713839202582__45725f46-1ba6-405c-95d4-d360b9a71f9f-text-1","template--19713839202582__45725f46-1ba6-405c-95d4-d360b9a71f9f-button-1"],"custom_css":["h2 {font-weight: 300; font-family: \"Poppins\";}","p {font-weight: 300; font-family: \"Poppins\"; line-height: 1.8;}"],"settings":{"color_scheme":"background-1","full_width":true,"margin_top":"no-indent","margin_bottom":"no-indent","padding_top":"xs","padding_bottom":"no-indent"}},"8c56d2e5-9685-4f40-a0e6-22a8d1b85096":{"type":"compare","custom_css":[".compare__text {text-decoration: none; font-weight: 300; font-family: \"Poppins\";}",".compare__box {justify-content: center;}"],"settings":{"heading":"","title":"","text":"","show_button":false,"button_style":"primary","button_label":"Explore Our Store","button_link":"","image_before":"shopify:\/\/shop_images\/2_2.png","image_after":"shopify:\/\/shop_images\/1_1.png","margin_top":"no-indent","margin_bottom":"no-indent","padding_top":"xs","padding_bottom":"xs"}},"featured_blog_2":{"type":"featured-blog","disabled":true,"settings":{"color_scheme":"background-1","color_scheme_card":"background-2","subheading":"","heading":"Latest Articles","heading_size":"h3","post_layout":"grid","image_width":"small","image_fit":"contain","icon_background":"background-2","blog":"news","post_limit":3,"post_limit_mobile":3,"show_image":true,"show_tags":true,"show_date":true,"show_author":true,"show_excerpt":false,"show_view_all":false,"show_view_all_mobile":true,"button_label":"Button label","button_style":"secondary","padding_top":"m","padding_bottom":"no-indent"}},"0012e989-f931-4e0b-9f41-21baac284a6e":{"type":"image-banner","disabled":true,"settings":{"full_width":true,"color_scheme":"background-1","subheading":"","heading":"","heading_size":"medium","text_information":"","text_align":"left","show_view_all":false,"button_label":"Shop now","button_style":"primary","button_link":"","image":"shopify:\/\/shop_images\/banner.png","image_ratio":"landscape","opacity_overlay":0,"margin_top":"no-indent","margin_bottom":"no-indent"}},"945a0815-ce2d-4012-b06b-9e3856bdc9d9":{"type":"newsletter","custom_css":["p {font-weight: 300; font-family: \"Poppins\";}"],"settings":{"align_content":"center","full_width":false,"heading":"<p>Our Newsletter<\/p>","newsletter_text":"<p>Get E-mail Updates About our latest special offers<\/p>","button_style":"primary","padding_top":"no-indent","padding_bottom":"no-indent"}}},"order":["48edaa1f-b582-470b-8d04-40d80341942b","5ed7c7e5-b0f1-42d6-9aa0-897eafcf4df6","cards-grid","56f7c8aa-88c7-485a-a999-271f3264f443","featured-products","f985f678-f3e0-4940-a56f-227b4d758eb8","product-promo","multicolumn","featured-product","popular-products","b1d9d440-f506-456a-86a8-3df1859c32e5","81962f3e-586c-417a-9567-dbeea81ebf11","2a8c50a3-1cc0-4611-a321-c6569ecb5710","dc026c9c-e5f6-4e93-8b42-f40b32773c40","categories-list","45725f46-1ba6-405c-95d4-d360b9a71f9f","8c56d2e5-9685-4f40-a0e6-22a8d1b85096","featured_blog_2","0012e989-f931-4e0b-9f41-21baac284a6e","945a0815-ce2d-4012-b06b-9e3856bdc9d9"]}